ssp/keras/__init__.py
ssp/keras/base_frequency_loss.py
ssp/keras/loss_functions.py
ssp/keras/callbacks/__init__.py
ssp/keras/callbacks/callbacks.py
ssp/keras/ops/__init__.py
ssp/keras/ops/helper.py
ssp/numpy/__init__.py
ssp/numpy/ssp.py
surface_similarity_parameter-1.0.3.dist-info/licenses/LICENSE
surface_similarity_parameter-1.0.3.dist-info/METADATA
surface_similarity_parameter-1.0.3.dist-info/WHEEL
surface_similarity_parameter-1.0.3.dist-info/top_level.txt
surface_similarity_parameter-1.0.3.dist-info/RECORD
