Metadata-Version: 2.4
Name: surface-similarity-parameter
Version: 1.0.3
Summary: Surface Similarity Parameter for Python
Author-email: Mathies Wedler <mathies.wedler@tuhh.de>
License: GPL-3.0-or-later
Project-URL: Homepage, https://github.com/MathiesW/2022-code-surface-similarity-parameter-ml-loss-metric
Project-URL: Source, https://github.com/MathiesW/2022-code-surface-similarity-parameter-ml-loss-metric
Classifier: Programming Language :: Python :: 3
Classifier: License :: OSI Approved :: GNU General Public License v3 or later (GPLv3+)
Classifier: Operating System :: OS Independent
Requires-Python: >=3.8
License-File: LICENSE
Requires-Dist: numpy
Requires-Dist: keras-fft
Provides-Extra: keras
Requires-Dist: keras>=3.0.0; extra == "keras"
Dynamic: license-file
